gradient_descent_the_ultimate_optimizer/__init__.py
gradient_descent_the_ultimate_optimizer/gdtuo.py
gradient_descent_the_ultimate_optimizer-1.0.dist-info/LICENSE
gradient_descent_the_ultimate_optimizer-1.0.dist-info/METADATA
gradient_descent_the_ultimate_optimizer-1.0.dist-info/WHEEL
gradient_descent_the_ultimate_optimizer-1.0.dist-info/top_level.txt
gradient_descent_the_ultimate_optimizer-1.0.dist-info/RECORD
