Metadata-Version: 2.1
Name: gradient-descent-the-ultimate-optimizer
Version: 1.0
Summary: Code for paper, Gradient Descent: The Ultimate Optimizer
Author: Kartik Chandra, Audrey Xie
Project-URL: Homepage, https://github.com/kach/gradient-descent-the-ultimate-optimizer
Classifier: Programming Language :: Python :: 3
Classifier: License :: OSI Approved :: MIT License
Classifier: Operating System :: OS Independent
Requires-Python: >=3.7
License-File: LICENSE
